pyspellrecommender/__init__.py
pyspellrecommender-0.1.1.dist-info/LICENSE
pyspellrecommender-0.1.1.dist-info/METADATA
pyspellrecommender-0.1.1.dist-info/WHEEL
pyspellrecommender-0.1.1.dist-info/top_level.txt
pyspellrecommender-0.1.1.dist-info/RECORD
