Metadata-Version: 2.1
Name: pyspellrecommender
Version: 0.1.1
Summary: A spelling checker package
Home-page: https://github.com/karkipy/pyspellrecommender
Author: Aashish Karki
Author-email: aashish.y2z@gmail.com
License: UNKNOWN
Platform: UNKNOWN
Classifier: Programming Language :: Python :: 3
Classifier: License :: OSI Approved :: MIT License
Classifier: Operating System :: OS Independent
